gradecalculatorpy/__init__.py
gradecalculatorpy/calculate_grade.py
gradecalculatorpy/construct_course.py
gradecalculatorpy/gradecalculatorpy.py
gradecalculatorpy/predict_final.py
gradecalculatorpy/update_grades.py
gradecalculatorpy-1.0.1.dist-info/METADATA
gradecalculatorpy-1.0.1.dist-info/WHEEL
gradecalculatorpy-1.0.1.dist-info/LICENSE
gradecalculatorpy-1.0.1.dist-info/RECORD
