Metadata-Version: 2.1
Name: gradecalculatorpy
Version: 1.0.1
Summary: A python package which helps calculate grades for a course.
Home-page: https://github.com/UBC-MDS/gradecalculatorpy
License: MIT
Author: Chen Lin, Edward Zhang, Shirley Zhang
Requires-Python: >=3.9,<4.0
Classifier: License :: OSI Approved :: MIT License
Classifier: Programming Language :: Python :: 3
Classifier: Programming Language :: Python :: 3.9
Classifier: Programming Language :: Python :: 3.10
Classifier: Programming Language :: Python :: 3.11
Requires-Dist: pandas (>=1.5.2,<2.0.0)
Requires-Dist: pytest-cov (>=4.0.0,<5.0.0)
Project-URL: Repository, https://github.com/UBC-MDS/gradecalculatorpy
